onehux_sso_client/__init__.py
onehux_sso_client/admin.py
onehux_sso_client/apps.py
onehux_sso_client/backends.py
onehux_sso_client/decorators.py
onehux_sso_client/middleware.py
onehux_sso_client/mixins.py
onehux_sso_client/models.py
onehux_sso_client/tasks.py
onehux_sso_client/tests.py
onehux_sso_client/urls.py
onehux_sso_client/utils-old.py
onehux_sso_client/utils.py
onehux_sso_client/views.py
onehux_sso_client/webhooks-v2.py
onehux_sso_client/webhooks.py
onehux_sso_client/management/commands/onehux_init.py
onehux_sso_client/migrations/0001_initial.py
onehux_sso_client/migrations/__init__.py
onehux_sso_client/templates/user_model_template.py
onehux_sso_client/templates/onehux_sso_client/403.html
onehux_sso_client/templates/onehux_sso_client/admin.html
onehux_sso_client/templates/onehux_sso_client/base.html
onehux_sso_client/templates/onehux_sso_client/dashboard.html
onehux_sso_client/templates/onehux_sso_client/developer_dashboard.html
onehux_sso_client/templates/onehux_sso_client/logout_confirm.html
onehux_sso_client/templates/onehux_sso_client/logout_success.html
onehux_sso_client/templates/onehux_sso_client/member_dashboard.html
onehux_sso_client/templates/onehux_sso_client/owner_dashboard.html
onehux_sso_client-2.3.1.dist-info/licenses/LICENSE
onehux_sso_client-2.3.1.dist-info/METADATA
onehux_sso_client-2.3.1.dist-info/WHEEL
onehux_sso_client-2.3.1.dist-info/top_level.txt
onehux_sso_client-2.3.1.dist-info/RECORD
