Metadata-Version: 2.4
Name: onehux-sso-client
Version: 2.3.1
Summary: Django client for Onehux Accounts SSO/SLO integration
Author-email: Onehux Team <support@onehux.com>
Requires-Python: >=3.8
License-File: LICENSE
Requires-Dist: django>=5.0
Requires-Dist: uuid6>=2025.0.1
Requires-Dist: pyjwt>=2.8.0
Dynamic: license-file
